README.md
setup.py
dictcopy/__init__.py
dictcopy/dictcopy.py
dictcopy.egg-info/PKG-INFO
dictcopy.egg-info/SOURCES.txt
dictcopy.egg-info/dependency_links.txt
dictcopy.egg-info/requires.txt
dictcopy.egg-info/top_level.txt