Metadata-Version: 2.1
Name: dictcopy
Version: 0.0.4
Summary: Dict copy
Home-page: UNKNOWN
Author: Jeff Aguilar
Author-email: jeff.aguilar.06@gmail.com
License: MIT
Keywords: dict,copy,clone
Platform: UNKNOWN
Classifier: Development Status :: 3 - Alpha
Classifier: Intended Audience :: Developers
Classifier: Topic :: Software Development :: Build Tools
Classifier: License :: OSI Approved :: MIT License
Classifier: Programming Language :: Python :: 3.6
Classifier: Programming Language :: Python :: 3.7
Classifier: Programming Language :: Python :: 3.8
Classifier: Programming Language :: Python :: 3.9
Requires-Python: >=3.6
